napalm_slither/__init__.py
napalm_slither/detector_info.py
napalm_slither/entry_point.py
napalm_slither/environment_setter.py
napalm_slither/init.py
napalm_slither/plugin.py
napalm_slither/slither_modules.py
napalm_slither/slither_tool_runner.py
templates/init/example_slither_module.py
napalm_slither-0.1.1.dist-info/LICENSE
napalm_slither-0.1.1.dist-info/METADATA
napalm_slither-0.1.1.dist-info/WHEEL
napalm_slither-0.1.1.dist-info/entry_points.txt
napalm_slither-0.1.1.dist-info/RECORD
