Metadata-Version: 2.1
Name: napalm-slither
Version: 0.1.1
Summary: Napalm slither plugin
License: AGPLv3
Author: Joran Honig
Author-email: joran.honig@consensys.net
Requires-Python: >=3.12,<4.0
Classifier: License :: Other/Proprietary License
Classifier: Programming Language :: Python :: 3
Requires-Dist: loguru (>=0.7.2,<0.8.0)
Requires-Dist: napalm-toolbox (>=0.1.4,<0.2.0)
Requires-Dist: slither-analyzer (>=0.10.0,<0.11.0)
Requires-Dist: toolz (>=0.12.1,<0.13.0)
